{
    "top_xp_gain": {
        "player_name": "Dub Tbow",
        "week_start": "2024-08-19",
        "start_experience": 697674551,
        "end_experience": 699827399,
        "experience_gain": 2152848
    },
    "top_raids_gain": {
        "player_name": "Dub Tbow",
        "week_start_date": "2024-08-19",
        "raids_start": 1156,
        "raids_end": 1175,
        "raids_increase": 19,
        "bosses_start": 61276,
        "bosses_end": 61425,
        "bosses_increase": 149
    },
    "top_bosses_gain": {
        "player_name": "Dub Tbow",
        "week_start_date": "2024-08-19",
        "raids_start": 1156,
        "raids_end": 1175,
        "raids_increase": 19,
        "bosses_start": 61276,
        "bosses_end": 61425,
        "bosses_increase": 149
    }
}